secure_json/__init__.py
secure_json/main.py
secure_json-1.1.0.dist-info/WHEEL
secure_json-1.1.0.dist-info/METADATA
secure_json-1.1.0.dist-info/RECORD
